spinspg/__init__.py
spinspg/automorphisms.json
spinspg/core.py
spinspg/group.py
spinspg/permutation.py
spinspg/pointgroup.py
spinspg/spin.py
spinspg/utils.py
spinspg-0.1.6.dist-info/licenses/LICENSE
spinspg-0.1.6.dist-info/METADATA
spinspg-0.1.6.dist-info/WHEEL
spinspg-0.1.6.dist-info/top_level.txt
spinspg-0.1.6.dist-info/RECORD
