Metadata-Version: 2.4
Name: spinspg
Version: 0.1.6
Summary: Python package for detecting spin space group on top of spglib
Author-email: Kohei Shinohara <kshinohara0508@gmail.com>
License: BSD 3-Clause License
Project-URL: homepage, https://github.com/spglib/spinspg
Project-URL: repository, https://github.com/spglib/spinspg
Classifier: Development Status :: 2 - Pre-Alpha
Classifier: Intended Audience :: Science/Research
Classifier: License :: OSI Approved :: BSD License
Classifier: Operating System :: OS Independent
Classifier: Programming Language :: Python
Classifier: Programming Language :: Python :: 3.9
Classifier: Programming Language :: Python :: 3.10
Classifier: Programming Language :: Python :: 3.11
Classifier: Programming Language :: Python :: 3.12
Classifier: Topic :: Scientific/Engineering :: Mathematics
Classifier: Topic :: Scientific/Engineering :: Physics
Requires-Python: >=3.9.0
License-File: LICENSE
Requires-Dist: setuptools
Requires-Dist: setuptools_scm
Requires-Dist: wheel
Requires-Dist: typing_extensions
Requires-Dist: numpy>=1.20.1
Requires-Dist: spglib>=2.5
Requires-Dist: hsnf>=0.3.15
Requires-Dist: spgrep>=0.3.2
Provides-Extra: dev
Requires-Dist: spgrep-modulation>=0.2.5; extra == "dev"
Requires-Dist: pytest; extra == "dev"
Requires-Dist: pytest-cov; extra == "dev"
Requires-Dist: pre-commit; extra == "dev"
Requires-Dist: black; extra == "dev"
Requires-Dist: mypy; extra == "dev"
Requires-Dist: toml; extra == "dev"
Provides-Extra: docs
Requires-Dist: importlib-metadata; extra == "docs"
Requires-Dist: sphinx; extra == "docs"
Requires-Dist: sphinx-autobuild; extra == "docs"
Requires-Dist: myst-parser; extra == "docs"
Requires-Dist: sphinx-book-theme; extra == "docs"
Requires-Dist: linkify-it-py; extra == "docs"
Requires-Dist: enum-tools[sphinx]; extra == "docs"
Dynamic: license-file
